{"v":"5.1.10","fr":25,"ip":0,"op":23,"w":600,"h":600,"nm":"266 fill","ddd":0,"assets":[],"layers":[{"ddd":0,"ind":2,"ty":4,"nm":"Shape Layer 1","sr":1,"ks":{"o":{"a":0,"k":100,"ix":11},"r":{"a":0,"k":0,"ix":10},"p":{"a":0,"k":[300,300,0],"ix":2},"a":{"a":0,"k":[0,0,0],"ix":1},"s":{"a":1,"k":[{"i":{"x":[0.667,0.667,0.667],"y":[1,1,1]},"o":{"x":[0.167,0.167,0.167],"y":[0.167,0.167,-4.167]},"n":["0p667_1_0p167_0p167","0p667_1_0p167_0p167","0p667_1_0p167_-4p167"],"t":0,"s":[50,50,100],"e":[106,106,100]},{"i":{"x":[0.833,0.833,0.833],"y":[1,1,1]},"o":{"x":[0.333,0.333,0.333],"y":[0,0,0]},"n":["0p833_1_0p333_0","0p833_1_0p333_0","0p833_1_0p333_0"],"t":10,"s":[106,106,100],"e":[97,97,100]},{"i":{"x":[0.833,0.833,0.833],"y":[1,1,1]},"o":{"x":[0.167,0.167,0.167],"y":[0,0,0]},"n":["0p833_1_0p167_0","0p833_1_0p167_0","0p833_1_0p167_0"],"t":13,"s":[97,97,100],"e":[102,102,100]},{"i":{"x":[0.833,0.833,0.833],"y":[1,1,1]},"o":{"x":[0.167,0.167,0.167],"y":[0,0,0]},"n":["0p833_1_0p167_0","0p833_1_0p167_0","0p833_1_0p167_0"],"t":16,"s":[102,102,100],"e":[99,99,100]},{"i":{"x":[0.833,0.833,0.833],"y":[1,1,1]},"o":{"x":[0.167,0.167,0.167],"y":[0,0,0]},"n":["0p833_1_0p167_0","0p833_1_0p167_0","0p833_1_0p167_0"],"t":18,"s":[99,99,100],"e":[101,101,100]},{"i":{"x":[0.833,0.833,0.833],"y":[1,1,1]},"o":{"x":[0.167,0.167,0.167],"y":[0,0,0]},"n":["0p833_1_0p167_0","0p833_1_0p167_0","0p833_1_0p167_0"],"t":20,"s":[101,101,100],"e":[100,100,100]},{"t":21}],"ix":6}},"ao":0,"shapes":[{"ty":"gr","it":[{"ind":0,"ty":"sh","ix":1,"ks":{"a":0,"k":{"i":[[3.28,5.049],[-3.261,14.973],[0,0],[-6.505,0.045],[-3.527,-5.087]],"o":[[-3.28,-5.049],[1.072,-4.923],[0,0],[15.947,-0.109],[5.964,8.602]],"v":[[-59.559,16.546],[-67.822,-17.327],[-68.411,-35.116],[-51.071,-32.739],[-20.446,-21.266]],"c":false},"ix":2},"nm":"Path 1","mn":"ADBE Vector Shape - Group","hd":false},{"ty":"tm","s":{"a":1,"k":[{"i":{"x":[0.833],"y":[0.833]},"o":{"x":[0.167],"y":[0.167]},"n":["0p833_0p833_0p167_0p167"],"t":6,"s":[100],"e":[0]},{"t":10}],"ix":1},"e":{"a":0,"k":100,"ix":2},"o":{"a":0,"k":0,"ix":3},"m":1,"ix":2,"nm":"Trim Paths 1","mn":"ADBE Vector Filter - Trim","hd":false},{"ty":"st","c":{"a":0,"k":[0.207843139768,0.203921571374,0.164705887437,1],"ix":3},"o":{"a":0,"k":100,"ix":4},"w":{"a":0,"k":9,"ix":5},"lc":2,"lj":1,"ml":4,"nm":"Stroke 1","mn":"ADBE Vector Graphic - Stroke","hd":false},{"ty":"tr","p":{"a":0,"k":[0,0],"ix":2},"a":{"a":0,"k":[0,0],"ix":1},"s":{"a":0,"k":[100,100],"ix":3},"r":{"a":0,"k":0,"ix":6},"o":{"a":0,"k":100,"ix":7},"sk":{"a":0,"k":0,"ix":4},"sa":{"a":0,"k":0,"ix":5},"nm":"Transform"}],"nm":"Shape 6","np":4,"cix":2,"ix":1,"mn":"ADBE Vector Group","hd":false},{"ty":"gr","it":[{"ind":0,"ty":"sh","ix":1,"ks":{"a":0,"k":{"i":[[-4.5,4],[-15.23,-1.692],[0,0],[-1.02,-6.424],[4.5,-4.25]],"o":[[4.5,-4],[6.75,0.75],[0,0],[2.5,15.75],[-7.61,7.187]],"v":[[18.25,-19],[50.5,-32.25],[68,-35.5],[68.25,-18],[61.5,14]],"c":false},"ix":2},"nm":"Path 1","mn":"ADBE Vector Shape - Group","hd":false},{"ty":"tm","s":{"a":0,"k":0,"ix":1},"e":{"a":1,"k":[{"i":{"x":[0.833],"y":[0.833]},"o":{"x":[0.167],"y":[0.167]},"n":["0p833_0p833_0p167_0p167"],"t":8,"s":[0],"e":[100]},{"t":12}],"ix":2},"o":{"a":0,"k":0,"ix":3},"m":1,"ix":2,"nm":"Trim Paths 1","mn":"ADBE Vector Filter - Trim","hd":false},{"ty":"st","c":{"a":0,"k":[0.207843139768,0.203921571374,0.164705887437,1],"ix":3},"o":{"a":0,"k":100,"ix":4},"w":{"a":0,"k":9,"ix":5},"lc":2,"lj":1,"ml":4,"nm":"Stroke 1","mn":"ADBE Vector Graphic - Stroke","hd":false},{"ty":"tr","p":{"a":0,"k":[0,0],"ix":2},"a":{"a":0,"k":[0,0],"ix":1},"s":{"a":0,"k":[100,100],"ix":3},"r":{"a":0,"k":0,"ix":6},"o":{"a":0,"k":100,"ix":7},"sk":{"a":0,"k":0,"ix":4},"sa":{"a":0,"k":0,"ix":5},"nm":"Transform"}],"nm":"Shape 5","np":4,"cix":2,"ix":2,"mn":"ADBE Vector Group","hd":false},{"ty":"gr","it":[{"ind":0,"ty":"sh","ix":1,"ks":{"a":0,"k":{"i":[[-0.389,4.051],[0,0],[-5.25,-36.5]],"o":[[3.625,-37.75],[0,0],[0.854,5.939]],"v":[[-27.125,18],[0.25,-40.25],[27.875,18]],"c":false},"ix":2},"nm":"Path 1","mn":"ADBE Vector Shape - Group","hd":false},{"ty":"tm","s":{"a":0,"k":0,"ix":1},"e":{"a":1,"k":[{"i":{"x":[0.833],"y":[0.833]},"o":{"x":[0.167],"y":[0.167]},"n":["0p833_0p833_0p167_0p167"],"t":3,"s":[0],"e":[100]},{"t":8}],"ix":2},"o":{"a":0,"k":0,"ix":3},"m":1,"ix":2,"nm":"Trim Paths 1","mn":"ADBE Vector Filter - Trim","hd":false},{"ty":"st","c":{"a":0,"k":[0.207843139768,0.203921571374,0.164705887437,1],"ix":3},"o":{"a":0,"k":100,"ix":4},"w":{"a":0,"k":9,"ix":5},"lc":2,"lj":1,"ml":4,"nm":"Stroke 1","mn":"ADBE Vector Graphic - Stroke","hd":false},{"ty":"tr","p":{"a":0,"k":[0,0],"ix":2},"a":{"a":0,"k":[0,0],"ix":1},"s":{"a":0,"k":[100,100],"ix":3},"r":{"a":0,"k":0,"ix":6},"o":{"a":0,"k":100,"ix":7},"sk":{"a":0,"k":0,"ix":4},"sa":{"a":0,"k":0,"ix":5},"nm":"Transform"}],"nm":"Shape 4","np":4,"cix":2,"ix":3,"mn":"ADBE Vector Group","hd":false},{"ty":"gr","it":[{"ind":0,"ty":"sh","ix":1,"ks":{"a":0,"k":{"i":[[34.5,0],[9.5,0],[-24.125,0],[-20.25,0],[0,23.25],[12.5,0],[0,-9.25]],"o":[[-34.5,0],[0,20.25],[29.25,0],[20.25,0],[-21,0],[-35.25,0],[0,-9]],"v":[[-44.25,16.25],[-88,16.75],[-43.125,64.5],[44.75,64],[88,17],[44,16.5],[0,63.25]],"c":true},"ix":2},"nm":"Path 1","mn":"ADBE Vector Shape - Group","hd":false},{"ty":"tm","s":{"a":0,"k":0,"ix":1},"e":{"a":1,"k":[{"i":{"x":[0.667],"y":[1]},"o":{"x":[0.167],"y":[0.167]},"n":["0p667_1_0p167_0p167"],"t":0,"s":[0],"e":[100]},{"t":9}],"ix":2},"o":{"a":0,"k":-57,"ix":3},"m":1,"ix":2,"nm":"Trim Paths 1","mn":"ADBE Vector Filter - Trim","hd":false},{"ty":"st","c":{"a":0,"k":[0.207843139768,0.203921571374,0.164705887437,1],"ix":3},"o":{"a":0,"k":100,"ix":4},"w":{"a":0,"k":9,"ix":5},"lc":2,"lj":1,"ml":4,"nm":"Stroke 1","mn":"ADBE Vector Graphic - Stroke","hd":false},{"ty":"tr","p":{"a":0,"k":[0,0],"ix":2},"a":{"a":0,"k":[0,0],"ix":1},"s":{"a":0,"k":[100,100],"ix":3},"r":{"a":0,"k":0,"ix":6},"o":{"a":0,"k":100,"ix":7},"sk":{"a":0,"k":0,"ix":4},"sa":{"a":0,"k":0,"ix":5},"nm":"Transform"}],"nm":"Shape 3","np":4,"cix":2,"ix":4,"mn":"ADBE Vector Group","hd":false},{"ty":"gr","it":[{"ind":0,"ty":"sh","ix":1,"ks":{"a":0,"k":{"i":[[0,-3.5],[-11.25,0],[0,5.5]],"o":[[0,5],[11.875,0],[0,-3.625]],"v":[[-15.969,64.25],[-0.25,79.938],[16.094,64]],"c":false},"ix":2},"nm":"Path 1","mn":"ADBE Vector Shape - Group","hd":false},{"ty":"tm","s":{"a":0,"k":0,"ix":1},"e":{"a":1,"k":[{"i":{"x":[0.833],"y":[0.833]},"o":{"x":[0.167],"y":[0.167]},"n":["0p833_0p833_0p167_0p167"],"t":7,"s":[0],"e":[100]},{"t":11}],"ix":2},"o":{"a":0,"k":0,"ix":3},"m":1,"ix":2,"nm":"Trim Paths 1","mn":"ADBE Vector Filter - Trim","hd":false},{"ty":"st","c":{"a":0,"k":[0.207843139768,0.203921571374,0.164705887437,1],"ix":3},"o":{"a":0,"k":100,"ix":4},"w":{"a":0,"k":9,"ix":5},"lc":2,"lj":1,"ml":4,"nm":"Stroke 1","mn":"ADBE Vector Graphic - Stroke","hd":false},{"ty":"tr","p":{"a":0,"k":[0,0],"ix":2},"a":{"a":0,"k":[0,0],"ix":1},"s":{"a":0,"k":[100,100],"ix":3},"r":{"a":0,"k":0,"ix":6},"o":{"a":0,"k":100,"ix":7},"sk":{"a":0,"k":0,"ix":4},"sa":{"a":0,"k":0,"ix":5},"nm":"Transform"}],"nm":"Shape 2","np":4,"cix":2,"ix":5,"mn":"ADBE Vector Group","hd":false},{"ty":"gr","it":[{"ind":0,"ty":"sh","ix":1,"ks":{"a":0,"k":{"i":[[0,0],[0,0],[-2.25,0],[-2.5,0],[0,0],[0,0]],"o":[[0,0],[0,0],[2.25,0],[2.5,0],[0,0],[0,0]],"v":[[-8.5,78.75],[-8.263,117.999],[-6.125,120.125],[5.75,120.125],[8,117.5],[8,78]],"c":false},"ix":2},"nm":"Path 1","mn":"ADBE Vector Shape - Group","hd":false},{"ty":"tm","s":{"a":0,"k":0,"ix":1},"e":{"a":1,"k":[{"i":{"x":[0.833],"y":[0.833]},"o":{"x":[0.167],"y":[0.167]},"n":["0p833_0p833_0p167_0p167"],"t":9,"s":[0],"e":[100]},{"t":14}],"ix":2},"o":{"a":0,"k":0,"ix":3},"m":1,"ix":2,"nm":"Trim Paths 1","mn":"ADBE Vector Filter - Trim","hd":false},{"ty":"st","c":{"a":0,"k":[0.207843139768,0.203921571374,0.164705887437,1],"ix":3},"o":{"a":0,"k":100,"ix":4},"w":{"a":0,"k":9,"ix":5},"lc":2,"lj":1,"ml":4,"nm":"Stroke 1","mn":"ADBE Vector Graphic - Stroke","hd":false},{"ty":"tr","p":{"a":0,"k":[0,0],"ix":2},"a":{"a":0,"k":[0,0],"ix":1},"s":{"a":0,"k":[100,100],"ix":3},"r":{"a":0,"k":0,"ix":6},"o":{"a":0,"k":100,"ix":7},"sk":{"a":0,"k":0,"ix":4},"sa":{"a":0,"k":0,"ix":5},"nm":"Transform"}],"nm":"Shape 1","np":4,"cix":2,"ix":6,"mn":"ADBE Vector Group","hd":false}],"ip":0,"op":250,"st":0,"bm":0},{"ddd":0,"ind":3,"ty":4,"nm":"Shape Layer 2","sr":1,"ks":{"o":{"a":0,"k":100,"ix":11},"r":{"a":0,"k":0,"ix":10},"p":{"a":0,"k":[300,300,0],"ix":2},"a":{"a":0,"k":[0,0,0],"ix":1},"s":{"a":0,"k":[100,100,100],"ix":6}},"ao":0,"shapes":[{"ty":"gr","it":[{"ind":0,"ty":"sh","ix":1,"ks":{"a":0,"k":{"i":[[13.42,0],[9.064,-24.867],[-7.625,-8],[-5.999,3.905],[-5.25,-8.75],[-16.393,1.155]],"o":[[-13.565,0],[14.255,0.411],[6.625,-9.25],[7.751,6.155],[7.25,-8.25],[-9.235,-23.407]],"v":[[-0.25,-64.25],[-48.005,-32.661],[-16.375,-18.25],[0.749,-38.655],[16.75,-17],[48.393,-32.905]],"c":true},"ix":2},"nm":"Path 1","mn":"ADBE Vector Shape - Group","hd":false},{"ty":"fl","c":{"a":0,"k":[1,0.941176474094,0.031372550875,1],"ix":4},"o":{"a":0,"k":100,"ix":5},"r":1,"nm":"Fill 1","mn":"ADBE Vector Graphic - Fill","hd":false},{"ty":"tr","p":{"a":0,"k":[-0.5,-26],"ix":2},"a":{"a":0,"k":[-0.5,-26],"ix":1},"s":{"a":1,"k":[{"i":{"x":[0.667,0.667],"y":[1,1]},"o":{"x":[0.167,0.167],"y":[0.167,0.167]},"n":["0p667_1_0p167_0p167","0p667_1_0p167_0p167"],"t":12,"s":[0,0],"e":[100,100]},{"t":17}],"ix":3},"r":{"a":0,"k":0,"ix":6},"o":{"a":0,"k":100,"ix":7},"sk":{"a":0,"k":0,"ix":4},"sa":{"a":0,"k":0,"ix":5},"nm":"Transform"}],"nm":"Shape 3","np":3,"cix":2,"ix":1,"mn":"ADBE Vector Group","hd":false},{"ty":"gr","it":[{"ind":0,"ty":"sh","ix":1,"ks":{"a":0,"k":{"i":[[23.25,0],[0,-8.75],[-21.75,0],[0,4.25]],"o":[[-26.375,0],[9.5,0],[21.25,0],[-3,0]],"v":[[46.375,28.813],[12,64.125],[47.25,64],[86.125,29.313]],"c":true},"ix":2},"nm":"Path 1","mn":"ADBE Vector Shape - Group","hd":false},{"ty":"fl","c":{"a":0,"k":[0,0.956862747669,0.721568644047,1],"ix":4},"o":{"a":0,"k":100,"ix":5},"r":1,"nm":"Fill 1","mn":"ADBE Vector Graphic - Fill","hd":false},{"ty":"tr","p":{"a":0,"k":[48,45],"ix":2},"a":{"a":0,"k":[48,45],"ix":1},"s":{"a":1,"k":[{"i":{"x":[0.833,0.833],"y":[0.833,0.833]},"o":{"x":[0.167,0.167],"y":[0.167,0.167]},"n":["0p833_0p833_0p167_0p167","0p833_0p833_0p167_0p167"],"t":9,"s":[0,0],"e":[100,100]},{"t":13}],"ix":3},"r":{"a":0,"k":0,"ix":6},"o":{"a":0,"k":100,"ix":7},"sk":{"a":0,"k":0,"ix":4},"sa":{"a":0,"k":0,"ix":5},"nm":"Transform"}],"nm":"Shape 2","np":3,"cix":2,"ix":2,"mn":"ADBE Vector Group","hd":false},{"ty":"gr","it":[{"ind":0,"ty":"sh","ix":1,"ks":{"a":0,"k":{"i":[[15,0],[7.5,0],[-13.625,0],[-11.75,0]],"o":[[-8,0],[0,12.75],[8.5,0],[0,-24.25]],"v":[[-45.875,28.625],[-85,28.75],[-45.625,64.5],[-11.75,64.75]],"c":true},"ix":2},"nm":"Path 1","mn":"ADBE Vector Shape - Group","hd":false},{"ty":"fl","c":{"a":0,"k":[0,0.956862747669,0.721568644047,1],"ix":4},"o":{"a":0,"k":100,"ix":5},"r":1,"nm":"Fill 1","mn":"ADBE Vector Graphic - Fill","hd":false},{"ty":"tr","p":{"a":0,"k":[-47.5,45],"ix":2},"a":{"a":0,"k":[-47.5,45],"ix":1},"s":{"a":1,"k":[{"i":{"x":[0.833,0.833],"y":[0.833,0.833]},"o":{"x":[0.167,0.167],"y":[0.167,0.167]},"n":["0p833_0p833_0p167_0p167","0p833_0p833_0p167_0p167"],"t":7,"s":[0,0],"e":[100,100]},{"t":11}],"ix":3},"r":{"a":0,"k":0,"ix":6},"o":{"a":0,"k":100,"ix":7},"sk":{"a":0,"k":0,"ix":4},"sa":{"a":0,"k":0,"ix":5},"nm":"Transform"}],"nm":"Shape 1","np":3,"cix":2,"ix":3,"mn":"ADBE Vector Group","hd":false},{"ty":"gr","it":[{"ind":0,"ty":"sh","ix":1,"ks":{"a":0,"k":{"i":[[3,-1],[1.5,-3.75],[6.5,2.25],[6.75,0.25],[-1,-9],[0,0],[-28,-0.25],[-3.5,-6],[-13.5,0],[-1.75,0.5],[-1.25,5.5],[0.75,-0.25],[6.5,-0.5],[8,-10.5]],"o":[[-3,1],[-6.25,-6],[-6.5,-2.25],[0.5,3.75],[1,9],[0,0],[28,0.25],[9.5,-25.75],[13.5,0],[1.75,-0.5],[1.25,-5.5],[-0.75,0.25],[-6.5,0.5],[-1.5,-2]],"v":[[0.25,-39],[-16.5,-18],[-33,-30.25],[-67.5,-33.75],[-68.25,-5.25],[-60.75,16.25],[-42.75,16.5],[0,53],[44.5,16.75],[60.5,16.25],[68.25,1.25],[68.25,-34.25],[42.75,-32.25],[16.75,-17]],"c":true},"ix":2},"nm":"Path 1","mn":"ADBE Vector Shape - Group","hd":false},{"ty":"fl","c":{"a":0,"k":[1,1,1,1],"ix":4},"o":{"a":0,"k":100,"ix":5},"r":1,"nm":"Fill 1","mn":"ADBE Vector Graphic - Fill","hd":false},{"ty":"tr","p":{"a":0,"k":[0,0],"ix":2},"a":{"a":0,"k":[0,0],"ix":1},"s":{"a":1,"k":[{"i":{"x":[0.833,0.833],"y":[0.833,0.833]},"o":{"x":[0.167,0.167],"y":[0.167,0.167]},"n":["0p833_0p833_0p167_0p167","0p833_0p833_0p167_0p167"],"t":9,"s":[0,0],"e":[100,100]},{"t":14}],"ix":3},"r":{"a":0,"k":0,"ix":6},"o":{"a":0,"k":100,"ix":7},"sk":{"a":0,"k":0,"ix":4},"sa":{"a":0,"k":0,"ix":5},"nm":"Transform"}],"nm":"Shape 5","np":3,"cix":2,"ix":4,"mn":"ADBE Vector Group","hd":false},{"ty":"gr","it":[{"ind":0,"ty":"sh","ix":1,"ks":{"a":0,"k":{"i":[[34.5,0],[9.5,0],[-24.125,0],[-20.25,0],[0,23.25],[12.5,0],[0,-9.25]],"o":[[-34.5,0],[0,20.25],[29.25,0],[20.25,0],[-21,0],[-35.25,0],[0,-9]],"v":[[-44.25,16.25],[-88,16.75],[-43.125,64.5],[44.75,64],[88,17],[44,16.5],[0,63.25]],"c":true},"ix":2},"nm":"Path 1","mn":"ADBE Vector Shape - Group","hd":false},{"ty":"fl","c":{"a":0,"k":[1,1,1,1],"ix":4},"o":{"a":0,"k":100,"ix":5},"r":1,"nm":"Fill 1","mn":"ADBE Vector Graphic - Fill","hd":false},{"ty":"tr","p":{"a":0,"k":[-0.5,46.5],"ix":2},"a":{"a":0,"k":[-0.5,46.5],"ix":1},"s":{"a":1,"k":[{"i":{"x":[0.833,0.833],"y":[0.833,0.833]},"o":{"x":[0.167,0.167],"y":[0.167,0.167]},"n":["0p833_0p833_0p167_0p167","0p833_0p833_0p167_0p167"],"t":4,"s":[0,0],"e":[100,100]},{"t":9}],"ix":3},"r":{"a":0,"k":0,"ix":6},"o":{"a":0,"k":100,"ix":7},"sk":{"a":0,"k":0,"ix":4},"sa":{"a":0,"k":0,"ix":5},"nm":"Transform"}],"nm":"Shape 4","np":3,"cix":2,"ix":5,"mn":"ADBE Vector Group","hd":false},{"ty":"gr","it":[{"ind":0,"ty":"sh","ix":1,"ks":{"a":0,"k":{"i":[[0.25,3.75],[0.25,-3],[-0.5,-2.25],[0,0],[0,0],[-0.75,1.75]],"o":[[-8.5,-1],[-0.25,3],[0.5,2.25],[0,0],[0,0],[0.75,-1.75]],"v":[[15.5,65.25],[-15.5,66.75],[-8.25,79.25],[-7.5,119.75],[7.75,119.75],[8,79]],"c":true},"ix":2},"nm":"Path 1","mn":"ADBE Vector Shape - Group","hd":false},{"ty":"fl","c":{"a":0,"k":[1,1,1,1],"ix":4},"o":{"a":0,"k":100,"ix":5},"r":1,"nm":"Fill 1","mn":"ADBE Vector Graphic - Fill","hd":false},{"ty":"tr","p":{"a":0,"k":[-2,96],"ix":2},"a":{"a":0,"k":[-2,96],"ix":1},"s":{"a":1,"k":[{"i":{"x":[0.833,0.833],"y":[0.833,0.833]},"o":{"x":[0.167,0.167],"y":[0.167,0.167]},"n":["0p833_0p833_0p167_0p167","0p833_0p833_0p167_0p167"],"t":12,"s":[0,0],"e":[100,100]},{"t":16}],"ix":3},"r":{"a":0,"k":0,"ix":6},"o":{"a":0,"k":100,"ix":7},"sk":{"a":0,"k":0,"ix":4},"sa":{"a":0,"k":0,"ix":5},"nm":"Transform"}],"nm":"Shape 6","np":3,"cix":2,"ix":6,"mn":"ADBE Vector Group","hd":false}],"ip":0,"op":250,"st":0,"bm":0}],"markers":[]}